{
  "model_id": "rfdetr-seg-small",
  "status": "probed",
  "result_type": "SegmentationResult",
  "result_attrs": [
    "backend",
    "cache_path",
    "debug",
    "device",
    "fallback_reason",
    "image_size",
    "kind",
    "latency_ms",
    "max_polygon_points",
    "metadata",
    "model_id",
    "model_loaded_from",
    "output_mode",
    "plot",
    "polygon_simplification_tolerance",
    "precision",
    "return_boxes",
    "return_masks",
    "return_polygons",
    "return_quality",
    "return_rle",
    "save",
    "save_image",
    "save_json",
    "segments",
    "show",
    "summary",
    "task",
    "to_coco",
    "to_csv",
    "to_dict",
    "to_json",
    "to_pandas",
    "warnings"
  ],
  "mask_format": "RFDETR_SEG_MASK_OUTPUT_NOT_EXPOSED",
  "recommendation": "No mask, masks, or detections[i].mask found on the result object. Blocker code: RFDETR_SEG_MASK_OUTPUT_NOT_EXPOSED"
}