{
  "schema": "smart_tool_coverage_ledger.v3",
  "note": "Classic weight-free interactive annotation tools. SEPARATE from the pretrained model leaderboard (GATE V3-13). No model weights -> only dependency licenses, all permissive.",
  "dataset": "coco_val2017_400_vsx:promptable-derived-from-GT",
  "tools": [
    {
      "tool_id": "classic-intelligent-scissors",
      "tool_family": "classic_smart_annotation",
      "task": "interactive_segmentation_refine",
      "requires_model_weights": false,
      "dependency_license": "OpenCV Apache-2.0",
      "commercial_safe": true,
      "redistribution_risk": "none (no weights; permissive deps only)",
      "gated_or_auth_required": false,
      "device": "cpu",
      "prompt_types": "polyline,polygon",
      "benchmark_dataset": "coco_val2017_400_vsx:promptable-derived-from-GT",
      "instances_evaluated": 40,
      "mean_iou": 0.7741,
      "boundary_iou": 0.796,
      "success_rate_at_iou_50": 0.925,
      "success_rate_at_iou_75": 0.75,
      "latency_ms_mean": 133.254,
      "cpu_only_ok": true,
      "final_state": "benchmark_passed",
      "evidence_artifact": "reports/v3_classic_smart_refine_benchmark.json",
      "description": "Live-wire minimum-cost contour through polyline points"
    },
    {
      "tool_id": "classic-grabcut",
      "tool_family": "classic_smart_annotation",
      "task": "interactive_segmentation_refine",
      "requires_model_weights": false,
      "dependency_license": "OpenCV Apache-2.0",
      "commercial_safe": true,
      "redistribution_risk": "none (no weights; permissive deps only)",
      "gated_or_auth_required": false,
      "device": "cpu",
      "prompt_types": "box,positive_points,negative_points,scribble",
      "benchmark_dataset": "coco_val2017_400_vsx:promptable-derived-from-GT",
      "instances_evaluated": 40,
      "mean_iou": 0.4232,
      "boundary_iou": 0.3584,
      "success_rate_at_iou_50": 0.35,
      "success_rate_at_iou_75": 0.125,
      "latency_ms_mean": 163.501,
      "cpu_only_ok": true,
      "final_state": "benchmark_passed",
      "evidence_artifact": "reports/v3_classic_smart_refine_benchmark.json",
      "description": "GrabCut GMM graph-cut from box + pos/neg point seeds"
    },
    {
      "tool_id": "classic-marker-watershed",
      "tool_family": "classic_smart_annotation",
      "task": "interactive_segmentation_refine",
      "requires_model_weights": false,
      "dependency_license": "OpenCV Apache-2.0",
      "commercial_safe": true,
      "redistribution_risk": "none (no weights; permissive deps only)",
      "gated_or_auth_required": false,
      "device": "cpu",
      "prompt_types": "box,positive_points,negative_points,scribble,polygon,polyline,mask_hint",
      "benchmark_dataset": "coco_val2017_400_vsx:promptable-derived-from-GT",
      "instances_evaluated": 40,
      "mean_iou": 0.3843,
      "boundary_iou": 0.3605,
      "success_rate_at_iou_50": 0.4,
      "success_rate_at_iou_75": 0.075,
      "latency_ms_mean": 1.284,
      "cpu_only_ok": true,
      "final_state": "benchmark_passed",
      "evidence_artifact": "reports/v3_classic_smart_refine_benchmark.json",
      "description": "Marker-controlled watershed from fg/bg seeds"
    },
    {
      "tool_id": "classic-edge-plus",
      "tool_family": "classic_smart_annotation",
      "task": "interactive_segmentation_refine",
      "requires_model_weights": false,
      "dependency_license": "OpenCV Apache-2.0 + scikit-image BSD-3",
      "commercial_safe": true,
      "redistribution_risk": "none (no weights; permissive deps only)",
      "gated_or_auth_required": false,
      "device": "cpu",
      "prompt_types": "box,positive_points,negative_points",
      "benchmark_dataset": "coco_val2017_400_vsx:promptable-derived-from-GT",
      "instances_evaluated": 40,
      "mean_iou": 0.3671,
      "boundary_iou": 0.3346,
      "success_rate_at_iou_50": 0.375,
      "success_rate_at_iou_75": 0.075,
      "latency_ms_mean": 166.591,
      "cpu_only_ok": true,
      "final_state": "benchmark_passed",
      "evidence_artifact": "reports/v3_classic_smart_refine_benchmark.json",
      "description": "GrabCut estimate cut along Canny edges + morphological cleanup"
    },
    {
      "tool_id": "classic-slic-graphcut",
      "tool_family": "classic_smart_annotation",
      "task": "interactive_segmentation_refine",
      "requires_model_weights": false,
      "dependency_license": "scikit-image BSD-3 + OpenCV Apache-2.0",
      "commercial_safe": true,
      "redistribution_risk": "none (no weights; permissive deps only)",
      "gated_or_auth_required": false,
      "device": "cpu",
      "prompt_types": "box,positive_points,negative_points",
      "benchmark_dataset": "coco_val2017_400_vsx:promptable-derived-from-GT",
      "instances_evaluated": 40,
      "mean_iou": 0.3333,
      "boundary_iou": 0.2895,
      "success_rate_at_iou_50": 0.2,
      "success_rate_at_iou_75": 0.025,
      "latency_ms_mean": 189.584,
      "cpu_only_ok": true,
      "final_state": "benchmark_passed",
      "evidence_artifact": "reports/v3_classic_smart_refine_benchmark.json",
      "description": "SLIC superpixels snapped to a GrabCut foreground estimate"
    },
    {
      "tool_id": "classic-random-walker",
      "tool_family": "classic_smart_annotation",
      "task": "interactive_segmentation_refine",
      "requires_model_weights": false,
      "dependency_license": "scikit-image BSD-3",
      "commercial_safe": true,
      "redistribution_risk": "none (no weights; permissive deps only)",
      "gated_or_auth_required": false,
      "device": "cpu",
      "prompt_types": "box,positive_points,negative_points,scribble,polygon,polyline,mask_hint",
      "benchmark_dataset": "coco_val2017_400_vsx:promptable-derived-from-GT",
      "instances_evaluated": 40,
      "mean_iou": 0.2699,
      "boundary_iou": 0.2336,
      "success_rate_at_iou_50": 0.225,
      "success_rate_at_iou_75": 0.025,
      "latency_ms_mean": 112.055,
      "cpu_only_ok": true,
      "final_state": "benchmark_passed",
      "evidence_artifact": "reports/v3_classic_smart_refine_benchmark.json",
      "description": "Random-walker diffusion segmentation from seeds"
    },
    {
      "tool_id": "classic-slic-rf-smooth",
      "tool_family": "classic_smart_annotation",
      "task": "interactive_segmentation_refine",
      "requires_model_weights": false,
      "dependency_license": "scikit-image BSD-3 + scikit-learn BSD-3",
      "commercial_safe": true,
      "redistribution_risk": "none (no weights; permissive deps only)",
      "gated_or_auth_required": false,
      "device": "cpu",
      "prompt_types": "box,positive_points,negative_points,scribble,polygon,polyline,mask_hint",
      "benchmark_dataset": "coco_val2017_400_vsx:promptable-derived-from-GT",
      "instances_evaluated": 40,
      "mean_iou": 0.135,
      "boundary_iou": 0.1183,
      "success_rate_at_iou_50": 0.025,
      "success_rate_at_iou_75": 0.0,
      "latency_ms_mean": 53.009,
      "cpu_only_ok": true,
      "final_state": "benchmark_passed",
      "evidence_artifact": "reports/v3_classic_smart_refine_benchmark.json",
      "description": "RandomForest over SLIC superpixels (boundary-snapped)"
    },
    {
      "tool_id": "classic-interactive-rf",
      "tool_family": "classic_smart_annotation",
      "task": "interactive_segmentation_refine",
      "requires_model_weights": false,
      "dependency_license": "scikit-learn BSD-3",
      "commercial_safe": true,
      "redistribution_risk": "none (no weights; permissive deps only)",
      "gated_or_auth_required": false,
      "device": "cpu",
      "prompt_types": "box,positive_points,negative_points,scribble,polygon,polyline,mask_hint",
      "benchmark_dataset": "coco_val2017_400_vsx:promptable-derived-from-GT",
      "instances_evaluated": 40,
      "mean_iou": 0.0999,
      "boundary_iou": 0.0752,
      "success_rate_at_iou_50": 0.0,
      "success_rate_at_iou_75": 0.0,
      "latency_ms_mean": 39.31,
      "cpu_only_ok": true,
      "final_state": "benchmark_passed",
      "evidence_artifact": "reports/v3_classic_smart_refine_benchmark.json",
      "description": "Per-pixel RandomForest classifier on colour+gradient features"
    }
  ]
}